flock.py
setup.py
flock.egg-info/PKG-INFO
flock.egg-info/SOURCES.txt
flock.egg-info/dependency_links.txt
flock.egg-info/top_level.txt